srsly/__init__.py
srsly/cli.py
srsly/workflow.tar.gz
srsly/tests/__init__.py
srsly/tests/test_cli.py
srslyrun-0.2.1.dist-info/LICENSE
srslyrun-0.2.1.dist-info/METADATA
srslyrun-0.2.1.dist-info/WHEEL
srslyrun-0.2.1.dist-info/entry_points.txt
srslyrun-0.2.1.dist-info/top_level.txt
srslyrun-0.2.1.dist-info/RECORD
