Metadata-Version: 2.1
Name: srslyrun
Version: 0.2.1
Summary: Not your grandma's NGS analysis - software for analyzing FASTQs from SRSLY libraries
Home-page: https://github.com/claretbio/srslyrun
Author: Camille Schwartz
Author-email: camille@claretbio.com
Classifier: Programming Language :: Python :: 3
Classifier: License :: OSI Approved :: MIT License
Classifier: Operating System :: OS Independent
Requires-Python: >=3.7
License-File: LICENSE
Requires-Dist: snakemake
Requires-Dist: umi-tools
Requires-Dist: pyyaml
Requires-Dist: srslyumi
Requires-Dist: pysam
